{
  "ids": {
    "Child": 4
  },
  "models": {
    "Child": {
      "1": "{\"firstName\":\"Child First name\",\"lastName\":\"Last Name\",\"middleNames\":\"\",\"dateOfBirth\":\"2012-07-30T07:41:45.667Z\",\"id\":\"1\"}",
      "2": "{\"firstName\":\"Child First name\",\"lastName\":\"Last Name\",\"middleNames\":\"\",\"dateOfBirth\":\"2012-07-30T07:41:45.667Z\",\"id\":\"2\"}",
      "3": "{\"firstName\":\"Child First name 2\",\"lastName\":\"Last Name second\",\"middleNames\":\"\",\"dateOfBirth\":\"2010-07-30T07:41:45.667Z\",\"id\":\"3\"}"
    }
  }
}